pythoncgi/__init__.py
pythoncgi/core.py
pythoncgi/utils.py
pythoncgi/__metadata__/DISCLIAIMER.md
pythoncgi/__metadata__/LICENSE
pythoncgi/__metadata__/README.md
pythoncgi/__metadata__/__init__.py
pythoncgi/__metadata__/requirements.txt
pythoncgi/example/basic_python_cgi.py
pythoncgi/example/byte_serving_cgi.py
pythoncgi/example/caching_101.py
pythoncgi/example/cors_cache_proxy.py
pythoncgi/example/template.html
pythoncgi/example/test.html
pythoncgi/example/test.png
pythoncgi/example/user_authentication.py
pythoncgi/example/web_full_stack.py
pythoncgi/example/zippyshare_remote_upload.py
pythoncgi-0.17.0.dist-info/METADATA
pythoncgi-0.17.0.dist-info/WHEEL
pythoncgi-0.17.0.dist-info/top_level.txt
pythoncgi-0.17.0.dist-info/RECORD
